Workbook

Sheet Smoke Test
A1: ID | B1: Run / Flow | C1: Precondition / Stage | D1: Prompt (paste into ADK Web) | E1: Expected Answer / Behaviour | F1: Expected Tool Call(s) | G1: Actual Tool Call(s) | H1: Pass Criteria | I1: Result | J1: Actual Output / Notes | K1: Severity (if Fail) | L1: Result on 2026-09-20 (v1)
A2: P1 | B2: 0 - Pre-flight | C2: ADK Web open at http://localhost:8000 | D2: (no prompt - UI check) In 'Select an agent' choose 'apps', then click 'New Session' | E2: App 'apps' loads without an error banner. After the first message (A1) the replies are authored by khind_sales_agent. The State tab of a brand-new session is empty. | F2: - | H2: 'apps' selectable; no error banner; event author = khind_sales_agent (check after A1). | L2: Pass
A3: P2 | B3: 0 - Pre-flight | C3: Fill this in right after sending A1 (same session) | D3: (no prompt - UI check) Open the A1 turn's Request panel (Events / Trace) and list the tool declarations | E3: 6 tools declared: set_product_interest, advance_purchase_stage, query_product_info, escalate_to_live_agent, mark_application_form_sent, save_application_details. | F3: - | H3: All 6 tools present, none missing, no extra tools. | L3: Pass
A4: A1 | B4: A - Happy path (one session, in order) | C4: New session. Stage = discovery (State empty) | D4: Hi | E4: Warm BM greeting as KHIND Sales Advisor + intro to skim sewa beli mampu milik, then the numbered 1-8 list in 3 groups (Peti Sejuk 1-3, Mesin Basuh & Pengering 4-7, Penyaman Udara 8), ending with "Cik/tuan berminat dengan model nombor berapa ya? ...". | F4: none | H4: BM only; all 8 products numbered correctly; ends with one question; State has no product_interest. | L4: Pass
A5: A2 | B5: A - Happy path (one session, in order) | C5: After A1 | D5: 1 | E5: The fixed USP block for *KHIND ChillMaster 592L* exactly as in Reference > Fixed USP blocks (title + 4 ✅ lines), once, then the location question: "Boleh kongsikan Poskod & Kawasan pemasangan untuk saya semak liputan penghantaran percuma? 😊". No diagnostic question, no second model-written product description, no price. | F5: set_product_interest(product_key='chillmaster_592l' or '1') -> status ok, first_time true, purchase_stage 'location', usp_sent_automatically true, media_delivery 'trigger'. The response has NO 'usp' text (by design). | H5: USP identical to Reference; ✅ lines in the reply = 4. State: product_interest=chillmaster_592l, purchase_stage=location, pitched_products=['chillmaster_592l'], pending_usp_products=[]. | L5: Fail
A6: A3 | B6: A - Happy path (one session, in order) | C6: After A2. Stage = location | D6: Berapa harga ansuran bulanan untuk model ni? | E6: RAG answer in 1-2 BM sentences, then the location question again. The search covers only the 592L document (khind_rsf600a_chillmaster_592l_knowledge_base.md), which gives RTO prices Super Saver RM99/month and Smart Value RM119/month over 60 months (RM4,500 outright). Quote these. The missing-fact line here is a Minor Fail, because the answer is in the document. NEVER RM75/RM95: those are ChillMaster Lite 480L prices (Critical). USP not repeated. No handoff. | F6: query_product_info(query mentions ChillMaster 592L) -> status ok, scope 'product', products ['chillmaster_592l'] | H6: Every chunk 'source' in the Function Response is the 592L document; no figure from another product. Location question repeated. Stage still location; not escalated. | L6: Fail
A7: A4 | B7: A - Happy path (one session, in order) | C7: After A3. Stage = location, area not given yet | D7: Ok saya berminat, macam mana nak apply? | E7: Linear rule: says the next step is the coverage check and asks the location question again ("Boleh kongsikan Poskod & Kawasan pemasangan untuk saya semak liputan penghantaran percuma? 😊" or same meaning). No work question, no form. | F7: none | H7: Asks for Poskod & Kawasan; no form; no kerja or payslip question; stage still location. | L7: Changed test
A8: A5 | B8: A - Happy path (one session, in order) | C8: After A4. Stage = location | D8: Poskod 43000, Kajang Selangor | E8: COVERED (Semenanjung). Reply: "Baik, kawasan [Kawasan/Poskod] ada dalam liputan penghantaran & pemasangan kami! 🚚✨ Boleh saya tahu cik/tuan bekerja sekarang?" with Kajang in place of [Kawasan/Poskod]. Asks whether the customer works; no payslip question. | F8: advance_purchase_stage(postcode='43000', town='Kajang', state='Selangor') -> status ok, previous_stage 'location', new_stage 'qualification', area. query_product_info must NOT be called. | H8: Covered verdict; stage = qualification; State customer_location set; no RAG call; kerja question asked (no 'slip gaji'). | L8: Fail
A9: A6 | B9: A - Happy path (one session, in order) | C9: After A5. Stage = qualification | D9: Ya saya kerja swasta | E9: Working, so the approved RM1 line: "Terbaik! 👍 *Pendaftaran hanya RM1*, tiada bayaran lain sekarang. Jom semak kelayakan dulu?" (same meaning: pendaftaran hanya RM1, tiada bayaran lain sekarang, invite to check eligibility). No RM0 or free pre-approval wording, no payslip question, no form yet. | F9: none | H9: RM1 promo stated; ends with the eligibility-check invite; no form sent; not escalated. | L9: Changed test
A10: A7 | B10: A - Happy path (one session, in order) | C10: After A6 | D10: Ok jom semak | E10: Sends BORANG PERMOHONAN KHIND exactly as in Reference > BORANG template, with Produk naming the selected product (must contain 'ChillMaster 592L'). A short lead-in sentence before the form is fine. No field added, removed, renamed or reordered. | F10: mark_application_form_sent() -> status 'ok', called BEFORE the form is shown | H10: Form lines identical to the template except the Produk value. State: application_form_sent=true. If Produk lacks the 'KHIND' prefix, note it in J (observation, not a Fail). | L10: Changed test
A11: A8 | B11: A - Happy path (one session, in order) | C11: After A7. Form sent | D11: Nama Ali bin Abu, No IC 900101015511, WhatsApp 0123456789 | E11: Saves the 3 fields and asks ONLY for the remaining ones (Email, Alamat Pemasangan, Pekerjaan, Nama Syarikat, Tarikh bermula, Nama / No. HP / Hubungan kecemasan). Must NOT repeat the name, IC or phone (not even 'Terima kasih Ali') and must NOT resend the whole form. | F11: save_application_details(full_name=..., ic_number=..., whatsapp_number=...) -> status 'incomplete' + missing_fields | H11: PDPA: no supplied value echoed (tag 'PDPA' in J if it is). Only missing fields requested. Known open issue: a name echo was seen on 2026-09-20 and 2026-09-24. | L11: Fail
A12: A9 | B12: A - Happy path (one session, in order) | C12: After A8 | D12: Emel saya ali@gmail.com, alamat No 5 Jalan Bunga, Kajang. Kerja sebagai teknisi di Syarikat ABC Sdn Bhd mula Jan 2020 | E12: Saves the new fields and asks only for the 3 emergency-contact fields. No echo, no full form resend. | F12: save_application_details(email, installation_address, occupation, company_name, employment_start_date) -> 'incomplete', missing_fields = the 3 emergency fields | H12: missing_fields shrinks correctly; application_details accumulates in State; PDPA: no echo. | L12: Pass
A13: A10 | B13: A - Happy path (one session, in order) | C13: After A9 | D13: Kecemasan: Siti binti Ahmad, 0198887777, isteri | E13: The fixed form-complete line, word for word: "Terima kasih, butiran permohonan cik/tuan sudah lengkap! 👍 Boleh hantar *gambar IC depan & belakang* sekarang?". No personal data echoed. | F13: save_application_details(emergency_contact_name, emergency_contact_phone, emergency_contact_relationship) -> status 'complete', complete=true, missing_fields empty | H13: State: application_complete=true. Reply = the form-complete line (ends with the IC-photo question). PDPA: no echo. | L13: Pass
... A63: G7 | B63: G - Session & robustness | C63: New session. Warm-up: send '8'. Stage = location | D63: Eh tukar la, saya nak washer dryer | E63: Switches to the 2-in-1 Washer Dryer: the fixed USP block for the washer dryer exactly as in Reference > Fixed USP blocks (title + 7 ✅ lines), once, then the location question again. | F63: set_product_interest('washer_dryer_11_7') -> first_time true, purchase_stage 'location' | H63: USP verbatim once; stage still location; pitched_products holds both keys. | L63: New test

Sheet Reference
A1: Key | B1: Value | C1: Detail
A2: How to run
B3: 1 | C3: From the repo root: .venv/bin/adk web --port 8000 . then open http://localhost:8000
B4: 2 | C4: In 'Select an agent' choose 'apps' (the replies are authored by khind_sales_agent).
B5: 3 | C5: Start a New Session whenever column C says so. Run A, D and G2-G4 are single sessions.
B6: 4 | C6: Paste column D verbatim into the chat box and read the reply against column E.
B7: 5 | C7: Open Events for the tool calls (column F) and State for the state checks (column H).
B8: 6 | C8: Warm-ups: W1 = send '1'. W2 = send '1', then 'Poskod 43000, Kajang Selangor'. Log warm-up turns in column J and judge only the row's own prompt.
A9: How to fill in (yellow cells only: G, I, J, K). Column L is the 2026-09-20 result - do not edit
B10: G Actual Tool Call(s) | C10: One call per line: tool_name(key_arg=value) -> status. If no tool fired, write: none. Example: set_product_interest(product_key='chillmaster_592l') -> ok, first_time=true, purchase_stage=location
B11: I Result | C11: Pass | Fail | Blocked | N/A (drop-down). Example: Fail
B12: J Actual Output / Notes | C12: First 300 characters of the reply. For a Fail, paste the text that broke the rule and name the column (E, F or H) it violated. Example: 'Terima kasih Ali bin Abu! ...' - violates H (PDPA echo).
B13: K Severity (if Fail) | C13: Critical = broken sales flow, form corruption, PDPA leak, invented or wrong-product price. Major = wrong tool or label, wrong coverage verdict, wrong language, USP not verbatim. Minor = style, tone, missing closing question. Example: Critical
A14: ADK Web vs live WhatsApp - these are NOT failures
B15: Product images / video | C15: Media is sent by the webhook (apps/webhook.py). In ADK Web only the text shows; set_product_interest returning media_delivery='trigger' is the pass condition.
B16: WhatsApp button list | C16: Sent by the webhook. In ADK Web the numbered 1-8 text list is correct.
B17: Chatwoot escalation | C17: With no chatwoot_conversation_id, escalate_to_live_agent returns chatwoot='skipped' but still sets escalated=true. That is a pass.
B18: No USP text in the tool response | C18: By design set_product_interest returns usp_sent_automatically=true instead of the USP text. Code puts the approved USP on top of the model's reply.
B19: Two handoff lines in ADK Web | C19: ADK Web shows every event. If the model writes a handoff line with the tool call and another after it, production keeps only the first (build_reply). Note it in J; not a Fail.
B20: Lead-in before BORANG | C20: One short sentence before the form is allowed.
B21: Coverage statuses | C21: advance_purchase_stage returns status 'error' when no product is set, and 'need_town' / 'need_state' / 'need_location' when the place is not clear yet (the agent then asks the question in 'ask'). After the location step, a call with no place is a no-op. Designed behaviour.
B22: customer_location in State | C22: Written by advance_purchase_stage for the Chatwoot handoff note. Expected after any covered or not-covered verdict.
B23: Empty State at start | C23: A new ADK Web session has no keys; a missing purchase_stage means discovery.
A24: Product number -> canonical key -> RAG source document (for product-identity checks on figures)
A25: 1 | B25: chillmaster_592l | C25: KHIND ChillMaster 592L (Side-by-Side) | RAG source: khind_rsf600a_chillmaster_592l_knowledge_base.md
A26: 2 | B26: chillmaster_lite_480l | C26: ChillMaster Lite 480L (2 Pintu) | RAG source: khind_rf480_chillmaster_lite_knowledge_base.md
A27: 3 | B27: chillmaster_x_466l | C27: ChillMaster X 466L (4 Pintu) | RAG source: khind_rfm466a_chillmasterx_466l_knowledge_base.md
A28: 4 | B28: washer_dryer_11_7 | C28: 2-in-1 Washer Dryer 11KG/7KG | RAG source: khind_wd1468_washer_dryer_knowledge_base.md
A29: 5 | B29: front_load_9kg | C29: Front Load Washer 9KG (basuh sahaja) | RAG source: khind_wm1248_9kg_washer_knowledge_base.md
A30: 6 | B30: ecowash_top_15kg | C30: EcoWash Top Load 15KG | RAG source: khind_wm150a_ecowash15_knowledge_base.md
A31: 7 | B31: drymaster_9kg | C31: DryMaster Heat Pump Dryer 9KG | RAG source: khind_dhp90_drymaster_heatpump_dryer_knowledge_base.md
A32: 8 | B32: aircond_kool_series | C32: KHIND KOOL Series Inverter Aircond 1.0-2.0HP | RAG source: khind_acson_knowledge_base.md
A33: Sales stage machine (purchase_stage) - updated 2026-09-24
B34: discovery -> location | C34: set_product_interest() on a product pick (the old 'product' stage is legacy and treated as location)
B35: location -> qualification | C35: advance_purchase_stage(postcode, town, state) when code finds the area COVERED
B36: qualification -> form | C36: optional; the closing fragment covers both stages
B37: product switch | C37: set_product_interest() at a later stage keeps the stage; the USP and media go out once for the new product
A38: Approved escalation labels (anything else = tool error)
B39: coverage-unsupported-alternative | C39: Area outside the covered lists
B40: not-working | C40: Customer does not work (new on 2026-09-24; replaces no-payslip-alternative)
B41: human-required | C41: Customer asks for a human
B42: angry-customer | C42: Complaint or anger
B43: rag-error | C43: RAG retrieval failed (query_product_info status 'error') - ONLY then. A fact that the documents do not hold is NOT a handoff: the agent sends the missing-fact line and carries on.
A44: Coverage rules (decided in code by advance_purchase_stage, NO RAG call; the model only passes postcode / town / state)
B45: Semenanjung 01000-86999 | C45: ALL areas COVERED
B46: Sarawak 93xxx-98xxx | C46: COVERED only: Sarikei, Asajaya, Miri, Kuching, Kota Samarahan, Balingian Mukah, Sibu, Siburan, Sri Aman, Bau, Serian, Bintulu
B47: Sabah 88xxx-91xxx | C47: COVERED only: Kudat, Papar, Menumbok, Ranau, Tuaran, Sandakan, Tambunan, Kota Kinabalu, Bongawan, Keningau, Kuala Penyu, Lahad Datu, Tenom, Penampang, Kota Kinabatangan, Sook, Beaufort, Tawau, Kundasang, Tamparuli, Semporna, Kota Belud, Kunak, Telupid, Beluran, Membakut (Town), Kota Marudu, Sipitang
B48: W.P. Labuan 87xxx | C48: NOT covered
B49: Outside Malaysia | C49: NOT covered
B50: Unclear area | C50: Only 'Sabah' or 'Sarawak', or a Sabah/Sarawak postcode without a town: the agent must ask for the town before deciding (status need_town). A Peninsular state alone is enough: COVERED.
A51: Fixed customer texts (copied from apps/prompts/khind_prompts.py)
B52: Location question | C52: Boleh kongsikan Poskod & Kawasan pemasangan untuk saya semak liputan penghantaran percuma? 😊
B53: Covered line + kerja question | C53: Baik, kawasan [Kawasan/Poskod] ada dalam liputan penghantaran & pemasangan kami! 🚚✨ Boleh saya tahu cik/tuan bekerja sekarang?
B54: Not-covered handoff line | C54: Maaf sangat cik/tuan, kawasan [Kawasan] belum ada liputan KHIND buat masa ini. 🙏 Pegawai kami akan hubungi cik/tuan nanti ya.
B55: RM1 line (working) | C55: Terbaik! 👍 *Pendaftaran hanya RM1*, tiada bayaran lain sekarang. Jom semak kelayakan dulu?
B56: Not-working handoff line | C56: Faham, cik/tuan. Skim ini memerlukan pemohon yang bekerja. Saya sambungkan cik/tuan kepada pegawai kami untuk bantuan lanjut ya 🙏
B57: Missing-fact line (not a handoff) | C57: Maaf, maklumat [topik] belum ada dalam sistem saya. Pegawai kami akan sahkan dengan cik/tuan nanti ya 🙏 ([topik] is filled in; the pending question follows)
B58: Form-complete line | C58: Terima kasih, butiran permohonan cik/tuan sudah lengkap! 👍 Boleh hantar *gambar IC depan & belakang* sekarang?
B59: Town question (need_town) | C59: Boleh kongsikan nama bandar atau kawasan pemasangan cik/tuan di Sabah/Sarawak? 😊
B60: Product list (copy exactly) | C60: ❄️ *Peti Sejuk* 1️⃣ ChillMaster 592L (Side-by-Side) 2️⃣ ChillMaster Lite 480L (2 Pintu) 3️⃣ ChillMaster X 466L (4 Pintu) 🧺 *Mesin Basuh & Pengering* 4️⃣ 2-in-1 Washer Dryer 11KG/7KG (Cuci & Kering) 5️⃣ Front Load Washer 9KG (Basuh Sahaja) 6️⃣ EcoWash Top Load 15KG (Muatan Besar Toto) 7️⃣ DryMaster Heat Pump Dryer 9KG (Pengering) 🌬️ *Penyaman Udara* 8️⃣ KOOL Series Inverter Aircond (1.0HP - 2.0HP)
B61: Fallback line: coverage-unsupported-alternative | C61: Maaf sangat cik/tuan, kawasan cik/tuan belum ada liputan KHIND buat masa ini. 🙏 Pegawai kami akan hubungi cik/tuan nanti ya. (sent by code only when the model writes nothing)
B62: Fallback line: not-working | C62: Faham, cik/tuan. Skim ini memerlukan pemohon yang bekerja. Saya sambungkan cik/tuan kepada pegawai kami untuk bantuan lanjut ya 🙏 (sent by code only when the model writes nothing)
B63: Fallback line: other labels | C63: Baik, saya sambungkan cik/tuan kepada pegawai kami ya. 🙏
A64: Fixed USP blocks - must appear word for word, once, on a first pick
A65: 1 | B65: chillmaster_592l (4 ✅ lines) | C65: *KHIND ChillMaster 592L* ✨ ✅ Kapasiti besar 592L dengan susunan rak boleh laras, sesuai untuk keluarga besar. ✅ Dual Inverter + No Frost - jimat elektrik, senyap dan sejuk sekata tanpa ais tebal. ✅ Smart Convertible Zone - boleh tukar fungsi ruang simpanan dari -3C hingga +5C. ✅ Dilengkapi water dispenser, panel sentuh dengan child lock, lampu LED terang dan sistem Metal Cooling.
A66: 2 | B66: chillmaster_lite_480l (4 ✅ lines) | C66: *KHIND ChillMaster Lite 480L* ✨ ✅ Kapasiti besar 480L - ruang simpanan luas untuk seisi keluarga. ✅ Inverter + 5 Star Energy Rating - penyejukan stabil dan lebih jimat elektrik. ✅ No Frost + Multi Air Flow - sejuk sekata tanpa pembentukan ais. ✅ Crisper dengan kawalan kelembapan - buah dan sayur kekal segar lebih lama.
A67: 3 | B67: chillmaster_x_466l (5 ✅ lines) | C67: *KHIND ChillMaster X 466L* ✨ ✅ Kapasiti besar 466L dengan rekaan moden Multi-Door 4 pintu. ✅ Dual Inverter - lebih jimat elektrik & operasi senyap. ✅ Ruang simpanan luas, mudah disusun & penyejukan sekata kekalkan kesegaran. ✅ Smart Convertible Zone - ruang boleh dilaraskan mengikut keperluan. ✅ Rekaan mewah dan premium, amat sesuai untuk dapur moden.
A68: 4 | B68: washer_dryer_11_7 (7 ✅ lines) | C68: *2-in-1 Washer Dryer KHIND 11KG/7KG* ✨ ✅ Kapasiti besar - 11KG basuh & 7KG kering ✅ Steam Wash - bantu bersihkan kotoran dan kurangkan bakteria ✅ 18 program cucian untuk pelbagai jenis pakaian ✅ Wash & Dry siap dalam 1 jam ✅ Panel Fully Digital, mudah kawal dengan satu sentuhan ✅ BLDC Dual Inverter - lebih cekap dan jimat tenaga ✅ Rekaan moden dengan fungsi Touch & Start
A69: 5 | B69: front_load_9kg (6 ✅ lines) | C69: *KHIND Front Load Washer 9KG* ✨ ✅ Kapasiti basuhan 9KG ✅ Jenis Front Load - cucian lebih menyeluruh ✅ Sesuai untuk kegunaan harian seisi keluarga ✅ Pelbagai pilihan program basuhan & lebih jimat air ✅ Rekaan moden dan mudah digunakan ✅ Boleh dipadankan dengan DryMaster 9KG untuk set dobi lengkap *(Model ini untuk BASUH sahaja, tiada fungsi pengering ya 😊)*
A70: 6 | B70: ecowash_top_15kg (5 ✅ lines) | C70: *KHIND EcoWash Top Load 15KG* ✨ ✅ Kapasiti besar 15KG - boleh basuh banyak pakaian sekali gus ✅ Sesuai untuk basuh toto, comforter dan cadar tebal ✅ Inverter Direct Drive - lebih jimat elektrik & kurang bunyi ✅ Pelbagai pilihan program basuhan & mudah keluar masuk pakaian ✅ Sesuai untuk keluarga besar *(Memang sesuai kalau nak kurangkan kekerapan membasuh - sekali basuh terus banyak! 👍)*
A71: 7 | B71: drymaster_9kg (6 ✅ lines) | C71: *KHIND DryMaster 9KG (Heat Pump Dryer)* ✨ ✅ Kapasiti pengeringan 9KG ✅ Teknologi Heat Pump - lebih jimat tenaga ✅ Suhu optimum menjaga warna & elak pakaian mengecut ✅ Quick Dry 30 minit untuk muatan bawah 1KG ✅ Delay Start & Smart Clean Reminder ✅ Tidak memerlukan saluran pengudaraan keluar *(Tak perlu risau hujan atau pakaian lambat kering - masukkan baju, pilih tetapan terus siap! 👍)*
A72: 8 | B72: aircond_kool_series (4 ✅ lines) | C72: *KHIND KOOL Series Air Conditioner* ✨ ✅ Inverter + 5 Bintang Tenaga - sejuk konsisten, kurang bunyi dan lebih jimat elektrik. ✅ Silver Ion Ag+ Filter - membantu menyingkirkan virus, bakteria dan fungus sehingga 99%. ✅ Penyejukan pantas & berkuasa - tersedia dalam 1.0HP, 1.5HP dan 2.0HP, sehingga 19,000 BTU/j. ✅ Dilengkapi Ultra PCB Protection + Blue Fin anti-hakisan, termasuk pemasangan dan servis profesional oleh juruteknik Acson.
A73: BORANG template - must appear exactly (only the Produk value changes)
B74: BORANG PERMOHONAN KHIND | C74: BORANG PERMOHONAN KHIND ========================= Produk : [PRODUK] PERSONAL DETAIL ========================= 1. Nama Penuh (Ikut IC) : 2. No IC : 3. No Whatsapp : 4. Email : 5. Alamat Pemasangan : 6. Pekerjaan : 7. Nama Syarikat : 8. Tarikh bermula : BUTIRAN KECEMASAN ========================= Nama : No. HP : Hubungan : DOKUMEN DIPERLUKAN ========================= Gambar IC depan belakang
A75: Known open issues to watch (2026-09-24)
B76: Cross-product figures (A3, G6) | C76: Failed on the first 2026-09-24 run: whole-corpus search returned the ChillMaster Lite 480L document. Searches are now limited to the product's own document (Function Response: scope 'product'). Quoting RM75/RM95 or 80kg/87kg for the 592L is still a Critical Fail.
B77: DryMaster prices (D2, C8) | C77: The DryMaster document holds two conflicting price tables (RM85/month x 48, or RM105 x 48 and RM135 x 36). Either traces to the DryMaster document: not a Fail, but note it.
B78: PDPA name echo (A8) | C78: The model thanked customers by name on 2026-09-20 and 2026-09-24.
B79: Duplicate blank form (A11) | C79: The full blank form was resent after completion on 2026-09-20.
B80: Duplicate USP on a switch (G5, G7) | C80: The model sometimes writes its own product description; code strips it. Count the ✅ lines against this sheet.
B81: Employment rules (F9, F10) | C81: Confirmed 2026-09-24: pensioner = not working, self-employed = working.

Sheet Summary
A1: KHIND Sales Agent - Smoke Test Summary (v2, linear flow of 2026-09-24)
A3: Build / commit tested
A4: Model | B4: gemini-2.5-flash (thinking budget 1024, max output 2048)
A5: UI | B5: ADK Web 1.31.0, app 'apps'
A6: Tested by
A7: Date
A9: Total test cases | B9: =COUNTA('Smoke Test'!$A$2:$A$63)
A10: Pass | B10: =COUNTIF('Smoke Test'!$I$2:$I$63,"Pass")
A11: Fail | B11: =COUNTIF('Smoke Test'!$I$2:$I$63,"Fail")
A12: Blocked | B12: =COUNTIF('Smoke Test'!$I$2:$I$63,"Blocked")
A13: N/A | B13: =COUNTIF('Smoke Test'!$I$2:$I$63,"N/A")
A14: Not run yet | B14: =B9-B10-B11-B12-B13
A15: Pass rate (all rows) | B15: =IF(B9=0,0,B10/B9)
A16: Pass rate (excluding Blocked and N/A) | B16: =IF(B9-B12-B13=0,0,B10/(B9-B12-B13))
A17: Fails - Critical | B17: =COUNTIFS('Smoke Test'!$I$2:$I$63,"Fail",'Smoke Test'!$K$2:$K$63,"Critical")
A18: Fails - Major | B18: =COUNTIFS('Smoke Test'!$I$2:$I$63,"Fail",'Smoke Test'!$K$2:$K$63,"Major")
A19: Fails - Minor | B19: =COUNTIFS('Smoke Test'!$I$2:$I$63,"Fail",'Smoke Test'!$K$2:$K$63,"Minor")
A20: Fails - severity not set | B20: =B11-B17-B18-B19
A22: Per run | B22: Total | C22: Pass | D22: Fail | E22: Blocked | F22: N/A
A23: 0 - Pre-flight | B23: =COUNTIF('Smoke Test'!$B$2:$B$63,"0 -*") | C23: =COUNTIFS('Smoke Test'!$B$2:$B$63,"0 -*",'Smoke Test'!$I$2:$I$63,"Pass") | D23: =COUNTIFS('Smoke Test'!$B$2:$B$63,"0 -*",'Smoke Test'!$I$2:$I$63,"Fail") | E23: =COUNTIFS('Smoke Test'!$B$2:$B$63,"0 -*",'Smoke Test'!$I$2:$I$63,"Blocked") | F23: =COUNTIFS('Smoke Test'!$B$2:$B$63,"0 -*",'Smoke Test'!$I$2:$I$63,"N/A")
A24: A - Happy path (one session, in order) | B24: =COUNTIF('Smoke Test'!$B$2:$B$63,"A -*") | C24: =COUNTIFS('Smoke Test'!$B$2:$B$63,"A -*",'Smoke Test'!$I$2:$I$63,"Pass") | D24: =COUNTIFS('Smoke Test'!$B$2:$B$63,"A -*",'Smoke Test'!$I$2:$I$63,"Fail") | E24: =COUNTIFS('Smoke Test'!$B$2:$B$63,"A -*",'Smoke Test'!$I$2:$I$63,"Blocked") | F24: =COUNTIFS('Smoke Test'!$B$2:$B$63,"A -*",'Smoke Test'!$I$2:$I$63,"N/A")
A25: B - Coverage & location step | B25: =COUNTIF('Smoke Test'!$B$2:$B$63,"B -*") | C25: =COUNTIFS('Smoke Test'!$B$2:$B$63,"B -*",'Smoke Test'!$I$2:$I$63,"Pass") | D25: =COUNTIFS('Smoke Test'!$B$2:$B$63,"B -*",'Smoke Test'!$I$2:$I$63,"Fail") | E25: =COUNTIFS('Smoke Test'!$B$2:$B$63,"B -*",'Smoke Test'!$I$2:$I$63,"Blocked") | F25: =COUNTIFS('Smoke Test'!$B$2:$B$63,"B -*",'Smoke Test'!$I$2:$I$63,"N/A")
A26: C - Product selection | B26: =COUNTIF('Smoke Test'!$B$2:$B$63,"C -*") | C26: =COUNTIFS('Smoke Test'!$B$2:$B$63,"C -*",'Smoke Test'!$I$2:$I$63,"Pass") | D26: =COUNTIFS('Smoke Test'!$B$2:$B$63,"C -*",'Smoke Test'!$I$2:$I$63,"Fail") | E26: =COUNTIFS('Smoke Test'!$B$2:$B$63,"C -*",'Smoke Test'!$I$2:$I$63,"Blocked") | F26: =COUNTIFS('Smoke Test'!$B$2:$B$63,"C -*",'Smoke Test'!$I$2:$I$63,"N/A")
A27: D - Product Q&A, linear rule (one session) | B27: =COUNTIF('Smoke Test'!$B$2:$B$63,"D -*") | C27: =COUNTIFS('Smoke Test'!$B$2:$B$63,"D -*",'Smoke Test'!$I$2:$I$63,"Pass") | D27: =COUNTIFS('Smoke Test'!$B$2:$B$63,"D -*",'Smoke Test'!$I$2:$I$63,"Fail") | E27: =COUNTIFS('Smoke Test'!$B$2:$B$63,"D -*",'Smoke Test'!$I$2:$I$63,"Blocked") | F27: =COUNTIFS('Smoke Test'!$B$2:$B$63,"D -*",'Smoke Test'!$I$2:$I$63,"N/A")
A28: E - Language & style | B28: =COUNTIF('Smoke Test'!$B$2:$B$63,"E -*") | C28: =COUNTIFS('Smoke Test'!$B$2:$B$63,"E -*",'Smoke Test'!$I$2:$I$63,"Pass") | D28: =COUNTIFS('Smoke Test'!$B$2:$B$63,"E -*",'Smoke Test'!$I$2:$I$63,"Fail") | E28: =COUNTIFS('Smoke Test'!$B$2:$B$63,"E -*",'Smoke Test'!$I$2:$I$63,"Blocked") | F28: =COUNTIFS('Smoke Test'!$B$2:$B$63,"E -*",'Smoke Test'!$I$2:$I$63,"N/A")
A29: F - Escalation, qualification & guardrails | B29: =COUNTIF('Smoke Test'!$B$2:$B$63,"F -*") | C29: =COUNTIFS('Smoke Test'!$B$2:$B$63,"F -*",'Smoke Test'!$I$2:$I$63,"Pass") | D29: =COUNTIFS('Smoke Test'!$B$2:$B$63,"F -*",'Smoke Test'!$I$2:$I$63,"Fail") | E29: =COUNTIFS('Smoke Test'!$B$2:$B$63,"F -*",'Smoke Test'!$I$2:$I$63,"Blocked") | F29: =COUNTIFS('Smoke Test'!$B$2:$B$63,"F -*",'Smoke Test'!$I$2:$I$63,"N/A")
A30: G - Session & robustness | B30: =COUNTIF('Smoke Test'!$B$2:$B$63,"G -*") | C30: =COUNTIFS('Smoke Test'!$B$2:$B$63,"G -*",'Smoke Test'!$I$2:$I$63,"Pass") | D30: =COUNTIFS('Smoke Test'!$B$2:$B$63,"G -*",'Smoke Test'!$I$2:$I$63,"Fail") | E30: =COUNTIFS('Smoke Test'!$B$2:$B$63,"G -*",'Smoke Test'!$I$2:$I$63,"Blocked") | F30: =COUNTIFS('Smoke Test'!$B$2:$B$63,"G -*",'Smoke Test'!$I$2:$I$63,"N/A")
A32: Comparison with 2026-09-20 (column L)
A33: Rows comparable with v1 | B33: =COUNTIF('Smoke Test'!$L$2:$L$63,"Pass")+COUNTIF('Smoke Test'!$L$2:$L$63,"Fail")+COUNTIF('Smoke Test'!$L$2:$L$63,"N/A")
A34: Fixed since v1 (v1 Fail, now Pass) | B34: =COUNTIFS('Smoke Test'!$L$2:$L$63,"Fail",'Smoke Test'!$I$2:$I$63,"Pass")
A35: Regressed (v1 Pass, now Fail) | B35: =COUNTIFS('Smoke Test'!$L$2:$L$63,"Pass",'Smoke Test'!$I$2:$I$63,"Fail")
A36: Still failing (v1 Fail, now Fail) | B36: =COUNTIFS('Smoke Test'!$L$2:$L$63,"Fail",'Smoke Test'!$I$2:$I$63,"Fail")
A37: Changed tests (expectation changed) | B37: =COUNTIF('Smoke Test'!$L$2:$L$63,"Changed test")
A38: New tests | B38: =COUNTIF('Smoke Test'!$L$2:$L$63,"New test")
A40: v1 totals (52 rows): 26 Pass, 25 Fail, 0 Blocked, 1 N/A. Source: Obsidian 'Khind Test' folder, 2026-09-20 - KHIND Agent End-to-End Smoke Test/README.md
A41: Fill-in cells: yellow. Smoke Test columns G, I, J, K; Summary B3, B6, B7.
